[
    {
        "英文名称": "LAURALKONIUM BROMIDE",
        "中文名称": "劳拉溴铵",
        "功能": "防腐剂",
        "主要用途": "此物质加入护肤品中能有效的预防护肤品的腐败变质的问题。",
        "副反应": "暂未见相关报道"
    },
    {
        "英文名称": "LAURALKONIUM CHLORIDE",
        "中文名称": "劳拉氯铵",
        "功能": "防腐剂",
        "主要用途": "此物质加入护肤品中能有效的预防护肤品的腐败变质的问题。",
        "副反应": "暂未见相关报道"
    },
    {
        "英文名称": "LAURAMIDE DEA",
        "中文名称": "月桂酰胺 DEA",
        "功能": "保湿剂",
        "主要用途": "属于天然的保湿因子，对皮肤具有保湿的作用。",
        "副反应": "暂未见相关报道"
    },
    {
        "英文名称": "LAURAMIDE/MYRISTAMIDE DEA",
        "中文名称": "月桂酰胺/肉豆蔻酰胺 DEA",
        "功能": "保湿剂",
        "主要用途": "属于天然的保湿因子，对皮肤具有保湿的作用。",
        "副反应": "暂未见相关报道"
    },
    {
        "英文名称": "LEAD ACETATE",
        "中文名称": "醋酸铅",
        "功能": "柔软剂",
        "主要用途": "此物质是增加护肤品的湿润性的作用。",
        "副反应": "暂未见相关报道"
    },
    {
        "英文名称": "LECITHINAMIDE DEA",
        "中文名称": "卵磷脂酰胺 DEA",
        "功能": "稳定剂",
        "主要用途": "加入护肤品中可以减慢反应,保持化学平衡,降低表面张力,防止光、热分解或氧化分解等作用。",
        "副反应": "暂未见相关报道"
    },
    {
        "英文名称": "LINOLEAMIDE DEA",
        "中文名称": "亚油酰胺 DEA",
        "功能": "稳定剂",
        "主要用途": "加入护肤品中可以减慢反应,保持化学平衡,降低表面张力,防止光、热分解或氧化分解等作用。",
        "副反应": "暂未见相关报道"
    },
    {
        "英文名称": "LITHIUM HYDROXIDE",
        "中文名称": "氢氧化锂",
        "功能": "稳定剂",
        "主要用途": "加入护肤品中可以减慢反应,保持化学平衡,降低表面张力,防止光、热分解或氧化分解等作用。",
        "副反应": "暂未见相关报道"
    },
    {
        "英文名称": "LITHIUM SULFIDE",
        "中文名称": "硫化锂",
        "功能": "表面活性剂",
        "主要用途": "加入护肤品中主要是会使其比较柔顺，甚至有相当的起泡性。",
        "副反应": "暂未见相关报道"
    },
    {
        "英文名称": "MAGNESIUM FLUORIDE",
        "中文名称": "氟化镁",
        "功能": "表面活性剂",
        "主要用途": "加入护肤品中主要是会使其比较柔顺，甚至有相当的起泡性。",
        "副反应": "暂未见相关报道"
    },
    {
        "英文名称": "MAGNESIUM FLUOROSILICATE",
        "中文名称": "氟硅酸镁",
        "功能": "表面活性剂",
        "主要用途": "加入护肤品中主要是会使其比较柔顺，甚至有相当的起泡性。",
        "副反应": "暂未见相关报道"
    },
    {
        "英文名称": "MAGNESIUM PEROXIDE",
        "中文名称": "过氧化镁",
        "功能": "表面活性剂",
        "主要用途": "加入护肤品中主要是会使其比较柔顺，甚至有相当的起泡性。",
        "副反应": "暂未见相关报道"
    },
    {
        "英文名称": "MAGNESIUM SULFIDE",
        "中文名称": "硫化镁",
        "功能": "乳化剂",
        "主要用途": "此物质加入护肤品中的作用是防粘及防熔化 在晶体外形成一层保护膜，防止空气及水分侵入，提高制品的防潮性。",
        "副反应": "暂未见相关报道"
    },
    {
        "英文名称": "MAGNESIUM THIOGLYCOLATE",
        "中文名称": "巯基乙酸镁",
        "功能": "乳化剂",
        "主要用途": "此物质加入护肤品中的作用是防粘及防熔化 在晶体外形成一层保护膜，防止空气及水分侵入，提高制品的防潮性。",
        "副反应": "暂未见相关报道"
    },
    {
        "英文名称": "MEA-BORATE",
        "中文名称": "硼酸 MEA盐",
        "功能": "乳化剂",
        "主要用途": "此物质加入护肤品中的作用是防粘及防熔化 在晶体外形成一层保护膜，防止空气及水分侵入，提高制品的防潮性。",
        "副反应": "暂未见相关报道"
    },
    {
        "英文名称": "MELAMINE PEROXIDE",
        "中文名称": "过氧化蜜胺",
        "功能": "乳化剂",
        "主要用途": "此物质加入护肤品中的作用是防粘及防熔化 在晶体外形成一层保护膜，防止空气及水分侵入，提高制品的防潮性。",
        "副反应": "暂未见相关报道"
    },
    {
        "英文名称": "6-METHYL COUMARIN",
        "中文名称": "6-甲基香豆素",
        "功能": "润肤剂",
        "主要用途": "此物质加入护肤品中的作用是帮助水润养分渗透肌肤，深度补水，长效保湿，令肌肤愈加水嫩剔透。",
        "副反应": "暂未见相关报道"
    },
    {
        "英文名称": "METHYL THIOGLYCOLATE",
        "中文名称": "巯基乙酸甲酯",
        "功能": "表面活性剂",
        "主要用途": "加入护肤品中主要是会使其比较柔顺，甚至有相当的起泡性。",
        "副反应": "暂未见相关报道"
    },
    {
        "英文名称": "METHYLETHANOLAMINE",
        "中文名称": "甲基乙醇胺",
        "功能": "抗静电剂",
        "主要用途": "此物质用于护肤品中的作用是消除静电对皮肤的损害。",
        "副反应": "暂未见相关报道"
    },
    {
        "英文名称": "MINKAMIDE DEA",
        "中文名称": "貂油酰胺 DEA",
        "功能": "增溶剂",
        "主要用途": "此物质加入护肤品中可以使水的表面张力开始会急剧下降，继而形成表面活性剂分子聚集的胶束。形成胶束时所用表面活性剂的浓度称为临界胶束浓度。当表面活性剂的浓度达到临界胶束浓度时，胶束能把油或固体微粒吸聚在亲油基的一端，因此可增大微溶物或不溶物的溶解度。",
        "副反应": "暂未见相关报道"
    },
    {
        "英文名称": "MIPA-BORATE",
        "中文名称": "硼酸 MIPA盐",
        "功能": "抗静电剂",
        "主要用途": "此物质用于护肤品中的作用是消除静电对皮肤的损害。",
        "副反应": "暂未见相关报道"
    },
    {
        "英文名称": "MIXED ISOPROPANOLAMINES",
        "中文名称": "异丙醇胺混合物",
        "功能": "润肤剂",
        "主要用途": "此物质加入护肤品中的作用是帮助水润养分渗透肌肤，深度补水，长效保湿，令肌肤愈加水嫩剔透。",
        "副反应": "暂未见相关报道"
    },
    {
        "英文名称": "m-PHENYLENEDIAMINE",
        "中文名称": "m-苯二胺",
        "功能": "柔润剂",
        "主要用途": "此物质加入护肤品中刺激胶原蛋白、弹力纤维和透明质酸增生，提高肌肤的含水量和锁水度，增加皮肤厚度以及减少细纹。",
        "副反应": "暂未见相关报道"
    },
    {
        "英文名称": "m-PHENYLENEDIAMINE SULFATE",
        "中文名称": "m-苯二胺硫酸盐",
        "功能": "乳化剂",
        "主要用途": "此物质加入护肤品中的作用是防粘及防熔化 在晶体外形成一层保护膜，防止空气及水分侵入，提高制品的防潮性。",
        "副反应": "暂未见相关报道"
    },
    {
        "英文名称": "MYRISTALKONIUM CHLORIDE",
        "中文名称": "肉豆蔻基二甲基苄基氯化铵",
        "功能": "非离子表面活性剂",
        "主要用途": "性能温和，有效降低其他表面活性剂的作用，泡沫丰富，有乳化分散、增容作用。",
        "副反应": "暂未见相关报道"
    },
    {
        "英文名称": "MYRISTALKONIUM SACCHARINATE",
        "中文名称": "肉豆蔻基二甲基苄基糖精铵",
        "功能": "抗氧化剂",
        "主要用途": "此化学物加入护肤品中的用途是温和的去除老废多余的角质，加强肌肤代谢。",
        "副反应": "暂未见相关报道"
    },
    {
        "英文名称": "MYRISTAMIDE DEA",
        "中文名称": "肉豆蔻酰胺 DEA",
        "功能": "保湿剂",
        "主要用途": "此物质加入护肤品中的作用是覆盖在皮肤上时，可以防止水分从表面蒸发，保湿效果非常显著。",
        "副反应": "暂未见相关报道"
    },
    {
        "英文名称": "N,N-BIS(2-HYDROXYETHYL)-p-PHENYLENEDIAMINE SULFATE",
        "中文名称": "N,N'-双(2-羟乙基)-对-苯二胺硫酸盐",
        "功能": "润滑剂",
        "主要用途": "本品用于产品中起到润肤的作用",
        "副反应": "暂未见相关报道"
    },
    {
        "英文名称": "N,N-DIMETHYL-p-PHENYLENEDIAMINE",
        "中文名称": "N,N-二甲基-P-苯二胺  （CI 76075）",
        "功能": "柔润剂",
        "主要用途": "此物质加入护肤品中刺激胶原蛋白、弹力纤维和透明质酸增生，提高肌肤的含水量和锁水度，增加皮肤厚度以及减少细纹。",
        "副反应": "暂未见相关报道"
    },
    {
        "英文名称": "N,N-DIMETHYL-p-PHENYLENEDIAMINE SULFATE",
        "中文名称": "N,N-二甲基-P-苯二胺硫酸盐",
        "功能": "增溶剂",
        "主要用途": "此物质在护肤品中的作用是增加难溶物的溶点。",
        "副反应": "暂未见相关报道"
    },
    {
        "英文名称": "1-NAPHTHOL",
        "中文名称": "1-萘酚(CI 76605)",
        "功能": "柔润剂",
        "主要用途": "此物质加入护肤品中可以滋润肌肤，赋予肌肤平滑的感觉。",
        "副反应": "暂未见相关报道"
    },
    {
        "英文名称": "NICOMETHANOL HYDROFLUORIDE",
        "中文名称": "尼克(甲)醇氢氟酸盐",
        "功能": "保湿剂",
        "主要用途": "此物质又称为B5，为维生素类药物,是辅酶A的组成部分，加入护肤品中的作用是增加皮肤润湿感。",
        "副反应": "暂未见相关报道"
    },
    {
        "英文名称": "NITROMETHANE",
        "中文名称": "硝甲烷",
        "功能": "非离子表面活性剂",
        "主要用途": "性能温和，有效降低其他表面活性剂的作用，泡沫丰富，有乳化分散、增容作用。",
        "副反应": "暂未见相关报道"
    },
    {
        "英文名称": "N-METHOXYETHYL-p-PHENYLENEDIAMINE HCL",
        "中文名称": "N-甲氧乙基-p-苯二胺 HCL",
        "功能": "抗氧化剂",
        "主要用途": "此化学物加入护肤品中的用途是温和的去除老废多余的角质，加强肌肤代谢。",
        "副反应": "暂未见相关报道"
    },
    {
        "英文名称": "N-PHENYL-p-PHENYLENEDIAMINE",
        "中文名称": "N-苯基-p-苯二胺; (CI 76085)",
        "功能": "乳化剂",
        "主要用途": "常用作油包水型乳化剂，是优良的滋润性物质。可使因缺少天然水分而干燥或粗糙的皮肤软化并得到恢复。它是通过延迟，而不是完全阻止水分透过表皮层来维持皮肤通常的含水量",
        "副反应": "暂未见相关报道"
    },
    {
        "英文名称": "N-PHENYL-p-PHENYLENEDIAMINE HCL",
        "中文名称": "N-苯基-p-苯二胺 HCl；(CI 76086)",
        "功能": "保湿剂",
        "主要用途": "此物质加入护肤品中有舒缓，滋润，放松功效，适合各种肤质。",
        "副反应": "暂未见相关报道"
    },
    {
        "英文名称": "N-PHENYL-p-PHENYLENEDIAMINE SULFATE",
        "中文名称": "N-苯基-p-苯二胺硫酸盐",
        "功能": "两性离子表面活性剂",
        "主要用途": "此物质的作用是刺激性小，易溶于水，对酸碱稳定，泡沫多，去污力强",
        "副反应": "暂未见相关报道"
    },
    {
        "英文名称": "OCTADECENYL AMMONIUM FLUORIDE",
        "中文名称": "氟化十八烯基铵",
        "功能": "保湿剂",
        "主要用途": "此物质加入护肤品中的作用是覆盖在皮肤上时，可以防止水分从表面蒸发，保湿效果非常显著。",
        "副反应": "暂未见相关报道"
    },
    {
        "英文名称": "OLAFLUR",
        "中文名称": "奥拉氟",
        "功能": "表面活性剂",
        "主要用途": "加入护肤品中主要是会使其比较柔顺，甚至有相当的起泡性。",
        "副反应": "暂未见相关报道"
    },
    {
        "英文名称": "OLEALKONIUM CHLORIDE",
        "中文名称": "油基二甲基苄基氯化铵",
        "功能": "保湿剂",
        "主要用途": "此物质加入护肤品中的作用是覆盖在皮肤上时，可以防止水分从表面蒸发，保湿效果非常显著。",
        "副反应": "暂未见相关报道"
    },
    {
        "英文名称": "OLIVAMIDE DEA",
        "中文名称": "橄榄油酰胺 DEA",
        "功能": "表面活性剂",
        "主要用途": "可起到乳化、清洁和护理等多种作用",
        "副反应": "暂未见相关报道"
    },
    {
        "英文名称": "OXALIC ACID",
        "中文名称": "草酸",
        "功能": "螯合剂",
        "主要用途": "可降低和控制金属离子浓度，具有一定的分散能力",
        "副反应": "接触皮肤和如果吞下有害,有严重损害眼睛的风险，应避免与皮肤和眼睛接触,如果接触眼睛,立即用大量清水冲洗。"
    },
    {
        "英文名称": "OXYQUINOLINE",
        "中文名称": "羟基喹啉",
        "功能": "防腐剂",
        "主要用途": "杀菌、消毒、防腐，具有较强的防霉菌作用",
        "副反应": "如果吞下有害，可能有不可逆转的影响，对眼睛、呼吸系统和皮肤有刺激，如果接触眼睛,立即用大量清水冲洗。动物实验显示有致癌性，化妆品中最大允许含量为0.3%，防晒产品和3岁以下儿童用品 (如爽身粉)禁用，并应在产品标签上注明“3岁以下儿童禁用”"
    },
    {
        "英文名称": "OXYQUINOLINE SULFATE",
        "中文名称": "羟基喹啉硫酸盐",
        "功能": "防腐剂、乳化稳定剂",
        "主要用途": "是一种强有力的金属螯合剂，能沉淀多种重金属，具有内吸杀菌活性，主要用于林业、医药、化工、化妆品等方面",
        "副反应": "如果吞下有毒"
    },
    {
        "英文名称": "PALM KERNELAMIDE DEA",
        "中文名称": "棕榈仁油酰胺 DEA",
        "功能": "乳化剂、表面活性剂、稠化剂",
        "主要用途": "使水和油混合成乳液状态，且可稳定乳化作用、控制粘度，从使稀薄的流体成为粘稠的膏霜",
        "副反应": "有一定的致粉性和刺激性"
    },
    {
        "英文名称": "PALMAMIDE DEA",
        "中文名称": "棕榈油酰胺 DEA",
        "功能": "乳化剂、表面活性剂、稠化剂",
        "主要用途": "使水和油混合成乳液状态，且可稳定乳化作用、控制粘度，从使稀薄的流体成为粘稠的膏霜",
        "副反应": "有一定的致粉性和刺激性"
    },
    {
        "英文名称": "PALMITAMIDE DEA",
        "中文名称": "棕榈酰胺 DEA",
        "功能": "表面活性剂、起泡剂、稠化剂、粘度控制剂",
        "主要用途": "具有乳化、分散、增溶抗静电性、湿润渗透等性能，使用中起发泡、洗净等作用",
        "副反应": "有一定的致粉性和刺激性"
    },
    {
        "英文名称": "PHENOL",
        "中文名称": "苯酚",
        "功能": "防腐剂",
        "主要用途": "具有杀菌、防腐作用",
        "副反应": "会引起脱皮、皮肤干燥"
    },
    {
        "英文名称": "POTASSIUM CHLORATE",
        "中文名称": "氯酸钾",
        "功能": "氧化剂",
        "主要用途": "可用作消毒，防腐",
        "副反应": "吸入和皮肤接触有害，对水生生物有毒,可能产生长期不良影响在水生环境"
    },
    {
        "英文名称": "POTASSIUM FLUORIDE",
        "中文名称": "氟化钾",
        "功能": "口腔粘膜用药",
        "主要用途": "用于漱口水、牙膏等口腔用品中起到消毒杀菌的作用",
        "副反应": "对人体皮肤、粘膜、眼睛有刺激性，吞下有毒性。如果接触眼睛,立即用大量清水冲洗。"
    },
    {
        "英文名称": "POTASSIUM FLUOROSILICATE",
        "中文名称": "氟硅酸钾",
        "功能": "口腔粘膜用药",
        "主要用途": "用于漱口水、牙膏等口腔用品中起到消毒杀菌的作用",
        "副反应": "对人体皮肤、粘膜、眼睛有刺激性。如果接触眼睛,立即用大量清水冲洗。"
    },
    {
        "英文名称": "POTASSIUM HYDROXIDE",
        "中文名称": "氢氧化钾",
        "功能": "酸碱调节剂、除毛剂",
        "主要用途": "强碱性物质，用以调整 pH值，并常加入植物酸中进行皂化程序，以制成肥皂，常用于清洁产品中。除此之外，由于其会破坏毛干的最外层表皮，也常用于除毛用品中",
        "副反应": "有皮肤刺激性"
    },
    {
        "英文名称": "POTASSIUM MONOFLUOROPHOSPHATE",
        "中文名称": "单氟磷酸钾",
        "功能": "口腔黏膜用药",
        "主要用途": "有杀菌作用，防龋齿效果好及脱敏作用，常用于牙膏中的活性添加剂",
        "副反应": "暂未见相关报道"
    },
    {
        "英文名称": "POTASSIUM SULFIDE",
        "中文名称": "硫化钾",
        "功能": "除毛剂",
        "主要用途": "高浓度下，脱毛效果显著，脱毛力强，但对皮肤刺激性大，防腐性强，而且在2%以下的低浓度，又无脱毛效果，常与其他碱土硫化物并用作为脱毛剂",
        "副反应": "与酸接触释放有毒气体，如果接触眼睛,立即用大量清水冲洗。因其高刺激性，为化妆品中限用物质，最高允许浓度用于脱毛剂时为2%(以硫计)"
    },
    {
        "英文名称": "POTASSIUM THIOGLYCOLATE",
        "中文名称": "巯基乙酸钾",
        "功能": "除毛剂、还原剂",
        "主要用途": "脱毛效果好，对皮肤刺激性低，在碱性条件下可迅速切断毛发，是一种较新型且理想的脱毛原料，近年来已逐步取代了许多传统化学脱毛剂，具有脱毛作用的还有巯基乙酸的钠盐、钙盐、镁盐、锶盐等，而常同时用两种以上的巯基乙酸盐作为脱毛剂原料效果更好",
        "副反应": "巯基乙酸盐用作脱毛剂时，其最大允许浓度为5%，在产品上必须说明含有“巯基乙酸盐，按说明使用”"
    },
    {
        "英文名称": "p-PHENYLENEDIAMINE",
        "中文名称": "p-苯二胺",
        "功能": "色料、染发剂",
        "主要用途": "白色至淡紫红色晶体。暴露在空气中变紫红色或深褐色",
        "副反应": "疾病控制与预防中心(CDC)将此成份列为接触式过敏源。常用于作为黑色染色添加物，卫生署规定产品中使用量不得超过4%。"
    },
    {
        "英文名称": "QUININE",
        "中文名称": "奎宁",
        "功能": "头发调理剂",
        "主要用途": "杀菌、消毒、止痒、保护头皮和使头发免遭细菌的侵害",
        "副反应": "如果吞下、吸入有毒，对眼睛刺激性，立即用大量清水冲洗。通过皮肤接触可能导致敏感，接触后,应立即清洗"
    },
    {
        "英文名称": "RESORCINOL",
        "中文名称": "间苯二酚",
        "功能": "防腐剂",
        "主要用途": "\r\n\r\n白色晶体酚类，具抗细菌与霉菌、收敛及止痒性质，常用于预防面疱，另外常用于抗头皮屑洗发液，或作化妆品防腐剂及染发剂。\r\n消毒杀菌，常见于慢性皮肤病药膏的成份，能减轻湿疹情。部份洗发液作添加作为抗屑成份。\r\n其杀菌作用为苯酚的1/3，其刺激性和腐蚀性也较小。低浓度有促进角质新生的作用，高浓度有角质剥离作用",
        "副反应": "可引起接触性皮炎，对皮肤、粘膜有弱的刺激性，如经破损的皮肤和创面大量吸收，可导致黏液性水肿。\r\n因本品可以经皮肤或溃疡面吸收，在婴儿和幼儿不宜高浓度、大面积使用。儿童在伤口上应用本品可发生正铁血红蛋白血症。\r\n中毒症状有腹泻、恶心、呕吐、胃痛、头晕、剧烈或持续头痛、疲乏或软弱、易激动或烦躁、昏沉思睡、盗汗、心动过缓、呼吸短促。\r\n由于本品有抗甲状腺作用，全身反应类似苯酚中毒，但常可发生惊厥"
    },
    {
        "英文名称": "RICINOLEAMIDE DEA",
        "中文名称": "蓖麻油酰胺 DEA",
        "功能": "表面活性剂、起泡剂、稠化剂、粘度控制剂",
        "主要用途": "具有乳化、分散、增溶抗静电性、湿润渗透等性能，使用中起发泡、洗净等作用",
        "副反应": "有一定的致粉性和刺激性"
    },
    {
        "英文名称": "SELENIUM SULFIDE",
        "中文名称": "硫化硒",
        "功能": "抑菌剂、去屑剂",
        "主要用途": "抗真菌，用于治疗头部脂溢性皮炎、脸部粉刺及躯体汗斑等",
        "副反应": "如果吞下、吸入有毒，有累积效应的危险"
    },
    {
        "英文名称": "SESAMIDE DEA",
        "中文名称": "脂麻油酰胺 DEA",
        "功能": "表面活性剂",
        "主要用途": "可起到乳化、清洁和护理等多种作用"
    },
    {
        "英文名称": "SODIUM CARBONATE PEROXIDE",
        "中文名称": "过氧化碳酸钠",
        "功能": "杀菌剂",
        "主要用途": "强氧化剂，可单独作为消毒杀菌剂、除味剂等",
        "副反应": "吞下有害，对皮肤有一定刺激性，严重损害眼睛的风险，如果接触眼睛,立即用大量清水冲洗。"
    },
    {
        "英文名称": "SODIUM FLUORIDE",
        "中文名称": "氟化钠",
        "功能": "口腔粘膜用药",
        "主要用途": "将氟化钠加到牙膏中能起到防龋作用，因为氟化物与牙釉质作用可在牙釉质表面形成氟磷灰石，提高牙釉质的硬度和抗酸能力，并可减少菌斑的形成,减少龋齿的发病率",
        "副反应": "能腐蚀皮肤、刺激黏膜，长期接触有损神经系统。"
    },
    {
        "英文名称": "SODIUM HYDROXIDE",
        "中文名称": "氢氧化钠",
        "功能": "酸碱调节剂",
        "主要用途": "强碱性物质，用以调整 pH值，并常加入植物酸中进行皂化程序，以制成肥皂。\r\n",
        "副反应": "具有较强的刺激性，不宜经常出现在卸妆类产品中。氢氧化钠跟月桂酸、肉豆蔻酸还有硬脂酸这种融合会形成皂基，对油性皮肤来说清洁力度较强，但缺点是会使皮肤变干，依个人情况而定，干性皮肤或者敏感肌不太适合"
    },
    {
        "英文名称": "SODIUM MONOFLUOROPHOSPHATE",
        "中文名称": "单氟磷酸钠",
        "功能": "口腔黏膜用药",
        "主要用途": "有杀菌作用，防龋齿效果好及脱敏作用，常用于牙膏中的活性添加剂",
        "副反应": "吸入或与眼睛、皮肤接触会引起刺激，皮肤长时间与其接触会导致大量吸入此物质。如果眼睛、口腔、皮肤沾染粉尘时，要立即用大量水冲洗，严重时要立即请医生诊治。"
    },
    {
        "英文名称": "SODIUM NITRITE",
        "中文名称": "亚硝酸钠",
        "功能": "防腐剂",
        "副反应": "皮肤接触亚硝酸钠溶液的极限浓度为1.5%，大于此浓度时皮肤会发炎，出现斑疹。误服本品3g可致眩晕、呕吐、处于意识丧失状态。"
    },
    {
        "英文名称": "SODIUM OXALATE",
        "中文名称": "草酸钠",
        "功能": "螯合剂",
        "副反应": "接触皮肤和吞下有害，避免与眼睛接触、如接触眼睛,立即用大量清水冲洗。"
    },
    {
        "英文名称": "SODIUM PERBORATE",
        "中文名称": "过硼酸钠",
        "功能": "氧化剂、漂白剂(洗衣清洁用途)",
        "主要用途": "用作氧化剂、消毒剂、杀菌剂、媒染剂、脱臭剂、具有防腐、脱臭、漂白和杀菌等作用，一般用于洗衣清洁作用",
        "副反应": "吞下有害、刺激呼吸系统、眼睛和皮肤，如果接触眼睛,立即用大量清水冲洗。"
    },
    {
        "英文名称": "SODIUM SULFIDE",
        "中文名称": "硫化钠",
        "功能": "除毛剂",
        "主要用途": "可去除毛发",
        "副反应": "硫化钠对皮肤有强腐蚀性，接触硫化钠溶液的工人手部皮肤发生皱裂，发红。操作时应加注意。误触皮肤，可用水冲洗。为了保护皮肤，建议经常用弱乙酸溶液擦手，然后涂以油质性软膏。注意保护眼睛，硫化钠飞沫或小块落入眼内立即用水冲洗15min后，送医院治疗。"
    },
    {
        "英文名称": "SODIUM THIOGLYCOLATE",
        "中文名称": "巯基乙酸钠",
        "功能": "除毛剂",
        "主要用途": "可去除毛发",
        "副反应": "如果吞下有害，刺激眼睛、呼吸系统和皮肤，如果接触眼睛,立即用大量清水冲洗。"
    },
    {
        "英文名称": "SOYAMIDE DEA",
        "中文名称": "大豆油脂酰胺 DEA",
        "功能": "乳化剂、表面活性剂、稠化剂",
        "主要用途": "使水和油混合成乳液状态，且可稳定乳化作用、控制粘度，从使稀薄的流体成为粘稠的膏霜",
        "副反应": "有一定的致粉性和刺激性"
    },
    {
        "英文名称": "STANNOUS FLUORIDE",
        "中文名称": "氟化亚锡",
        "功能": "口腔粘膜用药",
        "主要用途": "氟化亚锡具有氟离子和锡离子双重抗龋作用。亚锡离子作为表面活性剂，可阻止细菌豁附于牙面，从而减少菌斑的形成。亚锡离子可与变链菌细胞膜上的酸性物质发生作用，选择性抑制变链菌。氟化亚锡与牙齿接触时间延长后，锡与正磷酸作用，形成一层不溶性磷酸锡、氟化钙和磷酸氟化物",
        "副反应": "吞下有害，对皮肤刺激性，由吸入可能导致敏感"
    },
    {
        "英文名称": "STEARALKONIUM CHLORIDE",
        "中文名称": "司拉氯铵",
        "功能": "表面活性剂",
        "主要用途": "是一种阳离子性表面活性剂，常用于护发素中。它的亲水基团是带正电荷的，从而能够被头发受损蛋白部位的负电荷所吸引，不易被水洗掉，能够留在头发上起到护理的作用。且作为防腐剂应用于化妆品中。",
        "副反应": "高浓度对皮肤、眼睛有刺激性"
    },
    {
        "英文名称": "STEARAMIDE DEA",
        "中文名称": "硬脂酰胺 DEA",
        "功能": "表面活性剂",
        "主要用途": "非离子表面活性剂-聚醚型。具有优良的去污、乳化、发泡、稳泡、增稠、抗静电、增溶、分散、润滑、防锈、缓蚀能力。作为乳化剂、稳泡剂、增稠剂等，应用于个人护理用品领域。",
        "副反应": "最大使用浓度为小于17%时是安全的，该成分不应用于可能形成N一亚硝基化合物的化妆品中。"
    },
    {
        "英文名称": "STRONTIUM HYDROXIDE",
        "中文名称": "氢氧化锶",
        "功能": "酸碱调节剂",
        "主要用途": "一种白色粉末，在溶液态时是一种强碱，主要用于皂类制造",
        "副反应": "皮肤刺激"
    },
    {
        "英文名称": "STRONTIUM PEROXIDE",
        "中文名称": "过氧化锶",
        "功能": "漂白剂、抗菌剂",
        "主要用途": "一种白色粉末，广泛作为家庭及工业用漂白剂、洗涤剂、氧化剂。",
        "副反应": "该成分粉尘对眼睛、皮肤和呼吸系统有刺激作用。\r\n水溶液为碱性腐蚀液体。\r\n"
    },
    {
        "英文名称": "TALLAMIDE DEA",
        "中文名称": "妥尔油酰胺 DEA",
        "功能": "表面活性剂",
        "主要用途": "非离子表面活性剂-聚醚型。具有优良的去污、乳化、发泡、稳泡、增稠、抗静电、增溶、分散、润滑、防锈、缓蚀能力。作为乳化剂、稳泡剂、增稠剂等，应用于个人护理用品领域。",
        "副反应": "高浓度对皮肤、眼睛有刺激性"
    },
    {
        "英文名称": "TALLOWALKONIUM CHLORIDE",
        "中文名称": "牛脂基苄基二甲基氯化铵",
        "功能": "润肤剂、肌肤调理剂、爽肤剂、表面活性剂",
        "主要用途": "阳离子表面活性剂-季铵盐。具有优良的杀菌、抗菌、防腐、抗静电、分散、缓蚀、乳化能力。作为调理剂、爽肤剂、润肤剂、杀菌剂、防腐剂等，广泛应用于香波、浴露、护发素、润肤膏等个人护理用品领域。",
        "副反应": "高浓度对皮肤、眼睛有刺激性"
    },
    {
        "英文名称": "TALLOWAMIDE DEA",
        "中文名称": "牛油脂酰胺 DEA",
        "功能": "表面活性剂",
        "主要用途": "非离子表面活性剂-聚醚型。具有优良的去污、乳化、发泡、稳泡、增稠、抗静电、增溶、分散、润滑、防锈、缓蚀能力。作为乳化剂、稳泡剂、增稠剂等，应用于个人护理用品领域。",
        "副反应": "高浓度对皮肤、眼睛有刺激性"
    },
    {
        "英文名称": "TETRAPOTASSIUM ETIDRONATE",
        "中文名称": "羟乙磷酸四钾",
        "功能": "表面活性剂",
        "主要用途": "阴离子表面活性剂-磷酸盐（磷酸酯盐）。具有优良的螯合、分散、缓蚀能力。作为螯合剂等，应用于个人护理用品领域。",
        "副反应": "高浓度对皮肤、眼睛有刺激性"
    },
    {
        "英文名称": "TETRASODIUM ETIDRONATE",
        "中文名称": "羟乙磷酸四钠",
        "功能": "表面活性剂",
        "主要用途": "阴离子表面活性剂-磷酸盐（磷酸酯盐）。具有优良的螯合、分散、缓蚀能力。作为螯合剂等，应用于个人护理用品领域。",
        "副反应": "高浓度对皮肤、眼睛有刺激性"
    },
    {
        "英文名称": "TRIETHANOLAMINE",
        "中文名称": "三乙醇胺",
        "功能": "酸碱调节剂、表面活性剂",
        "主要用途": "非离子表面活性剂-胺。具有优良的抗静电、分散、缓蚀、润滑、去污、乳化能力。作为缓冲剂、乳化剂等，应用于个人护理用品领域。",
        "副反应": "易引起皮肤刺激及过敏反应，美国化粧品成分评估委员会(CIR) 指出在沖洗产品中还算安全，但长期接触性产品需注意，建议小心使用，与脂肪酸作用会产生皂化反应。  由于其为胺类物质，具有产生亚硝胺之潜在可能，不过一般三乙醇胺在化妆品中添加量并不多，且目前并无亚硝胺会穿透皮肤之报告，因此应不需太过担心。"
    },
    {
        "英文名称": "TRIISOPROPANOLAMINE",
        "中文名称": "三异丙醇胺",
        "功能": "酸碱调节剂",
        "主要用途": "非离子表面活性剂-胺。具有优良的抗静电、分散、缓蚀、润滑、去污、乳化能力。作为缓冲剂等，应用于个人护理用品领域。",
        "副反应": "临床试验表明，含有不超过1.1%三异丙醇胺的化妆品是极微弱的皮肤刺激剂和接触致敏剂。"
    },
    {
        "英文名称": "TRIOCTYLDODECYL BORATE",
        "中文名称": "三个辛基十二烷醇硼酸酯",
        "功能": "润肤剂、肌肤调理剂、表面活性剂",
        "主要用途": "非离子表面活性剂-硼酸酯。具有优良的抗磨、分散、乳化、润滑、防锈能力。作为调理剂、润肤剂等，应用于个人护理用品领域。",
        "副反应": "高浓度对皮肤、眼睛有刺激性"
    },
    {
        "英文名称": "TROMETHAMINE",
        "中文名称": "氨丁三醇",
        "功能": "酸碱调节剂",
        "主要用途": "非离子表面活性剂-胺。具有优良的抗静电、分散、缓蚀、润滑、去污、乳化能力。作为缓冲剂等，应用于个人护理用品领域。",
        "副反应": "高浓度对皮肤、眼睛有刺激性"
    },
    {
        "英文名称": "UNDECYLENAMIDE DEA",
        "中文名称": "十一碳烯酰胺 DEA",
        "功能": "杀菌剂、表面活性剂",
        "主要用途": "非离子表面活性剂-聚醚型。具有优良的杀菌、防腐、去污、乳化、发泡、稳泡、增稠、抗静电、增溶、分散、润滑、防锈、缓蚀能力。作为杀菌剂、去头屑剂、乳化剂、稳泡剂、增稠剂等，应用于个人护理用品领域。",
        "副反应": "高浓度对皮肤、眼睛有刺激性"
    },
    {
        "英文名称": "WHEAT GERMAMIDE DEA",
        "中文名称": "麦胚油酰胺 DEA",
        "功能": "表面活性剂",
        "主要用途": "非离子表面活性剂-聚醚型。具有优良的去污、乳化、发泡、稳泡、增稠、抗静电、增溶、分散、润滑、防锈、缓蚀能力。作为乳化剂、调理剂、稳泡剂、增稠剂等，应用于个人护理用品领域。",
        "副反应": "高浓度对皮肤、眼睛有刺激性"
    },
    {
        "英文名称": "ZINC ACETATE",
        "中文名称": "乙酸锌",
        "功能": "杀菌剂",
        "主要用途": "阴离子表面活性剂-羧酸盐。具有优良的防腐、杀菌、分散、杀菌能力。作为杀菌剂等，应用于个人护理用品领域。",
        "副反应": "高浓度对皮肤、眼睛有刺激性"
    },
    {
        "英文名称": "ZINC ASPARTATE",
        "中文名称": "天冬氨酸锌",
        "功能": "肌肤调理剂、表面活性剂",
        "主要用途": "两性离子表面活性剂-氨基酸型。具有优良的乳化、分散、抗静电能力。作为调理剂等，应用于个人护理用品领域。",
        "副反应": "高浓度对皮肤、眼睛有刺激性"
    },
    {
        "英文名称": "ZINC GLUCOHEPTONATE",
        "中文名称": "葡庚糖酸锌",
        "功能": "表面活性剂",
        "主要用途": "阴离子表面活性剂-羧酸盐。具有优良的乳化、分散、缓蚀能力。作为调理剂等，应用于个人护理用品领域。",
        "副反应": "高浓度对皮肤、眼睛有刺激性"
    },
    {
        "英文名称": "ZINC GLUCONATE",
        "中文名称": "葡糖酸锌",
        "功能": "控油、肌肤调理剂、表面活性剂",
        "主要用途": "阴离子表面活性剂-羧酸盐。具有优良的防锈、缓蚀、分散、乳化能力。作为除臭剂、肌肤调理剂、控油(调节皮脂分泌量)成分，用于化妆品中。",
        "副反应": "高浓度对皮肤、眼睛有刺激性"
    },
    {
        "英文名称": "ZINC GLUTAMATE",
        "中文名称": "谷氨酸锌",
        "功能": "肌肤调理剂、表面活性剂",
        "主要用途": "两性离子表面活性剂-氨基酸型。具有优良的分散、乳化、抗静电能力。作为调理剂等，应用于个人护理用品领域。",
        "副反应": "高浓度对皮肤、眼睛有刺激性"
    },
    {
        "英文名称": "ZINC HYDROLYZED COLLAGEN",
        "中文名称": "水解胶原锌盐",
        "功能": "肌肤调理剂、表面活性剂",
        "主要用途": "两性离子表面活性剂-氨基酸型。具有优良的乳化、分散、去污、抗静电能力。作为调理剂、抗静电剂等，应用于个人护理用品领域。与皮肤的相容性佳。",
        "副反应": "高浓度对皮肤、眼睛有刺激性"
    },
    {
        "英文名称": "ZINC LACTATE",
        "中文名称": "乳酸锌",
        "功能": "除臭剂",
        "主要用途": "阴离子表面活性剂-羧酸盐。具有优良的乳化、分散能力。作为除臭剂等，应用于个人护理用品领域。",
        "副反应": "高浓度对皮肤、眼睛有刺激性"
    },
    {
        "英文名称": "ZINC PCA",
        "中文名称": "吡咯烷酮羧酸锌",
        "功能": "保湿剂、肌肤调理剂",
        "主要用途": "控油成份，调节皮脂分泌量，能降低脂化酵素的活性，短时间内即有效果。",
        "副反应": "暂未见相关报道"
    },
    {
        "英文名称": "ZINC PENTADECENE TRICARBOXYLATE",
        "中文名称": "十五碳烯三羧酸锌",
        "功能": "表面活性剂",
        "主要用途": "阴离子表面活性剂-羧酸盐。具有优良的乳化、分散、润滑能力。作为调理剂、抗结剂等，应用于个人护理用品领域。",
        "副反应": "高浓度对皮肤、眼睛有刺激性"
    },
    {
        "英文名称": "ZINC PHENOLSULFONATE",
        "中文名称": "苯酚磺酸锌",
        "功能": "杀菌剂、收敛剂",
        "主要用途": "一种酚类具有收敛性质。阴离子表面活性剂-磺酸盐。具有良好的杀菌、防腐、抗菌、分散性能。作为杀菌剂、除臭剂、止汗剂等，应用于个人护理用品领域。",
        "副反应": "高浓度对皮肤、眼睛有刺激性"
    },
    {
        "英文名称": "ZINC SULFATE",
        "中文名称": "硫酸锌",
        "功能": "杀菌剂",
        "主要用途": "无色晶体，水溶性化合物。除杀菌之外还能防止产品变色。",
        "副反应": "暂未见相关报道"
    },
    {
        "英文名称": "ZINC YEAST DERIVATIVE",
        "中文名称": "锌酵母衍生物",
        "功能": "肌肤调理剂",
        "主要用途": "/",
        "副反应": "暂未见相关报道"
    },
    {
        "英文名称": "ALMONDAMIDE DEA",
        "中文名称": "杏仁油酰胺 DEA",
        "功能": "发泡剂、稳泡剂、增稠剂、去污剂、乳化剂、分散剂",
        "主要用途": "淡黄色至黄棕色液体；微溶于水；稳定。易氧化。具有良好的乳化、发泡、稳泡、增稠、去污、分散能力。作为发泡剂、稳泡剂、增稠剂、去污剂、乳化剂、分散剂等，广泛应用于个人护理用品等领域。",
        "副反应": "刺激。对皮肤、眼睛有刺激性。因二乙醇胺的可能致癌原因，应控制使用量。不建议用于婴幼儿用品中。"
    },
    {
        "英文名称": "ALUMINIUM ZIRCONIUM OCTACHLOROHYDRATE",
        "中文名称": "八氯羟铝锆",
        "功能": "止汗剂、除臭剂、收敛剂",
        "主要用途": "白色至黄棕色固体；或无色至黄棕色液体；溶于水；稳定。具有优良的絮凝、分散能力。可形成胶体。作为止汗剂、除臭剂、收敛剂等，应用于个人护理用品等领域。",
        "副反应": "刺激。对皮肤、眼睛有刺激性。"
    },
    {
        "英文名称": "ALUMINIUM ZIRCONIUM OCTACHLOROHYDREX GLYCINE",
        "中文名称": "八氯羟铝锆 GLY配位化合物",
        "功能": "止汗剂、除臭剂、收敛剂",
        "主要用途": "白色至黄棕色固体；或无色至黄棕色液体；溶于水；稳定。具有优良的絮凝、分散能力。可形成胶体。作为止汗剂、除臭剂、收敛剂等，应用于个人护理用品等领域。",
        "副反应": "刺激。对皮肤、眼睛有刺激性。"
    },
    {
        "英文名称": "ALUMINIUM ZIRCONIUM PENTACHLOROHYDRATE",
        "中文名称": "五氯羟铝锆",
        "功能": "止汗剂、除臭剂、收敛剂",
        "主要用途": "白色至黄棕色固体；或无色至黄棕色液体；溶于水；稳定。具有优良的絮凝、分散能力。可形成胶体。作为止汗剂、除臭剂、收敛剂等，应用于个人护理用品等领域。",
        "副反应": "刺激。对皮肤、眼睛有刺激性。"
    },
    {
        "英文名称": "ALUMINIUM ZIRCONIUM PENTACHLOROHYDREX GLYCINE",
        "中文名称": "五氯羟铝锆 GLY配位化合物",
        "功能": "止汗剂、除臭剂、收敛剂",
        "主要用途": "白色至黄棕色固体；或无色至黄棕色液体；溶于水；稳定。具有优良的絮凝、分散能力。可形成胶体。作为止汗剂、除臭剂、收敛剂等，应用于个人护理用品等领域。",
        "副反应": "刺激。对皮肤、眼睛有刺激性。"
    },
    {
        "英文名称": "ALUMINIUM ZIRCONIUM TETRACHLOROHYDRATE",
        "中文名称": "四氯羟铝锆",
        "功能": "止汗剂、除臭剂、收敛剂",
        "主要用途": "白色至黄棕色固体或无色至黄棕色液体；溶于水；稳定。具有优良的絮凝、分散能力。可形成胶体。作为止汗剂、除臭剂、收敛剂等，应用于个人护理用品等领域。",
        "副反应": "刺激。对皮肤、眼睛有刺激性。"
    },
    {
        "英文名称": "ALUMINIUM ZIRCONIUM TETRACHLOROHYDREX GLYCINE",
        "中文名称": "四氯羟铝锆 GLY配位化合物",
        "功能": "止汗剂、除臭剂、收敛剂",
        "主要用途": "白色至黄棕色固体或无色至黄棕色液体；溶于水；稳定。具有优良的絮凝、分散能力。可形成胶体。作为止汗剂、除臭剂、收敛剂等，应用于个人护理用品等领域。",
        "副反应": "刺激。对皮肤、眼睛有刺激性。"
    },
    {
        "英文名称": "ALUMINIUM ZIRCONIUM TETRACHLOROHYDREX PEG",
        "中文名称": "四氯羟铝锆  PEG配位化合物",
        "功能": "止汗剂、除臭剂、收敛剂",
        "主要用途": "无色至黄棕色液体；溶于水；稳定。具有优良的絮凝、分散能力。可形成胶体。作为止汗剂、除臭剂、收敛剂等，应用于个人护理用品等领域。",
        "副反应": "刺激。对皮肤、眼睛有刺激性。"
    },
    {
        "英文名称": "ALUMINIUM ZIRCONIUM TETRACHLOROHYDREX PG",
        "中文名称": "四氯羟铝锆  PG配位化合物",
        "功能": "止汗剂、除臭剂、收敛剂",
        "主要用途": "无色至黄棕色液体；溶于水；稳定。具有优良的絮凝、分散能力。可形成胶体。作为止汗剂、除臭剂、收敛剂等，应用于个人护理用品等领域。",
        "副反应": "刺激。对皮肤、眼睛有刺激性。"
    },
    {
        "英文名称": "ALUMINIUM ZIRCONIUM TRICHLOROHYDRATE",
        "中文名称": "三氯羟铝锆",
        "功能": "止汗剂、除臭剂、收敛剂",
        "主要用途": "白色至黄棕色固体；或无色至黄棕色液体；溶于水；稳定。具有优良的絮凝、分散能力。可形成胶体。作为止汗剂、除臭剂、收敛剂等，应用于个人护理用品等领域。",
        "副反应": "刺激。对皮肤、眼睛有刺激性"
    },
    {
        "英文名称": "ALUMINIUM ZIRCONIUM TRICHLOROHYDREX GLY",
        "中文名称": "三氯羟铝锆 GLY配位化合物",
        "功能": "止汗剂、除臭剂、收敛剂",
        "主要用途": "白色至黄棕色固体；或无色至黄棕色液体；溶于水；稳定。具有优良的絮凝、分散能力。可形成胶体。作为止汗剂、除臭剂、收敛剂等，应用于个人护理用品等领域。",
        "副反应": "刺激。对皮肤、眼睛有刺激性。"
    },
    {
        "英文名称": "2-AMINOBUTANOL",
        "中文名称": "2-氨基丁醇",
        "功能": "乳化剂、分散剂、酸碱调节剂",
        "主要用途": "具备很好的乳化、分散能力。可以中和部分酸性物质，作为酸碱调节剂。",
        "副反应": "刺激。对皮肤、眼睛有刺激性。"
    },
    {
        "英文名称": "AMINOMETHYL PROPANEDIOL",
        "中文名称": "氨甲基丙二醇",
        "功能": "缓冲剂、溶剂、去污剂、乳化剂、分散剂",
        "主要用途": "固体；溶于水；稳定。具有优良的去污、增溶、分散、乳化能力。作为缓冲剂、溶剂、去污剂、乳化剂、分散剂，应用于个人护理用品领域。",
        "副反应": "刺激。对皮肤、眼睛有刺激性。"
    },
    {
        "英文名称": "AMINOMETHYL PROPANOL",
        "中文名称": "氨甲基丙醇",
        "功能": "缓冲剂、溶剂、去污剂、分散剂、乳化剂",
        "主要用途": "固体；溶于水；稳定。具有优良的去污、增溶、分散、乳化能力。作为缓冲剂、溶剂、去污剂、分散剂、乳化剂，应用于个人护理用品领域。",
        "副反应": "刺激。对皮肤、眼睛有刺激性。"
    },
    {
        "英文名称": "AMMONIA",
        "中文名称": "氨"
    },
    {
        "英文名称": "AMMONIUM THIOGLYCOLATE",
        "中文名称": "巯基乙酸铵",
        "功能": "脱毛剂、去角质剂、还原剂",
        "主要用途": "无色至微红色液体或固体；强烈的难闻气味；易溶于水；稳定。易氧化。具有优良的抗氧化、分散、毛发脱除能力。作为脱毛剂、去角质剂、还原剂等，应用于染烫发剂、脱毛剂等个人护理用品领域。",
        "副反应": "具有刺激性。对皮肤、眼睛有刺激性。"
    },
    {
        "英文名称": "APRICOTAMIDE DEA",
        "中文名称": "杏仁油酰胺 DEA",
        "功能": "发泡剂、稳泡剂、增稠剂、去污剂、乳化剂、分散剂",
        "主要用途": "淡黄色至黄棕色液体；微溶于水；稳定。易氧化。具有良好的乳化、发泡、稳泡、增稠、去污、分散能力。作为发泡剂、稳泡剂、增稠剂、去污剂、乳化剂、分散剂等，广泛应用于个人护理用品等领域。",
        "副反应": "因二乙醇胺的可能致癌原因，应控制使用量。不建议用于婴幼儿用品中。刺激。对皮肤、眼睛有刺激性。"
    },
    {
        "英文名称": "AVOCADAMIDE DEA",
        "中文名称": "鳄梨油酰胺 DEA",
        "功能": "去污剂、乳化剂、发泡剂、稳泡剂、乳化稳定剂、增稠剂",
        "主要用途": "微黄色至淡黄色液体；微溶于水；稳定。易氧化。具有优良的去污、乳化、分散、发泡、稳泡、增溶、增稠能力。作为去污剂、乳化剂、发泡剂、稳泡剂、乳化稳定剂、增稠剂等，应用于个人护理用品领域",
        "副反应": "刺激。对皮肤、眼睛有刺激性。\r\n因二乙醇胺可能的致癌作用，应控制使用量。不建议应用于婴幼儿产品中。"
    },
    {
        "英文名称": "BABASSUAMIDE DEA",
        "中文名称": "巴巴苏油酰胺 DEA",
        "功能": "去污剂、乳化剂、增稠剂、发泡剂、调理剂、稳泡剂",
        "主要用途": "微黄色至淡黄色液体；微溶于水；或可溶于水（缔合体）；稳定。\r\n具有优良的去污、乳化、分散、发泡、稳泡、增溶、增稠能力。作为去污剂、乳化剂、增稠剂、发泡剂、调理剂、稳泡剂等，应用于个人护理用品领域。",
        "副反应": "刺激。对皮肤、眼睛有刺激性。因二乙醇胺可能的致癌作用，应控制使用量。不建议应用于婴幼儿产品中。"
    },
    {
        "英文名称": "BEHENAMIDE DEA",
        "中文名称": "山嵛酰胺 DEA",
        "功能": "去污剂、乳化剂、发泡剂、增稠剂、稳泡剂、润滑剂",
        "主要用途": "固体；微溶于水；稳定。具有优良的去污、乳化、分散、发泡、稳泡、增稠、润滑能力。作为去污剂、乳化剂、发泡剂、增稠剂、稳泡剂、润滑剂等，应用于个人护理用品领域。",
        "副反应": "刺激。对皮肤、眼睛有刺激性。"
    },
    {
        "英文名称": "BENZALKONIUM BROMIDE",
        "中文名称": "苯扎溴铵",
        "功能": "杀菌剂、调理剂",
        "主要用途": "具有优良的杀菌、抗菌、防腐、抗静电、缓蚀、润湿、渗透、分散、乳化、发泡能力。耐光。耐酸。耐硬水。无积累毒性。毒性低于十二烷基二甲基苄基氯化铵。杀菌能力优于十二烷基二甲基苄基氯化铵。作为杀菌剂、调理剂等，广泛应用于香波等个人护理用品领域。",
        "副反应": "具有刺激性。对皮肤、眼睛有较强的刺激性。"
    },
    {
        "英文名称": "BENZALKONIUM CHLORIDE",
        "中文名称": "苯扎氯铵",
        "功能": "杀菌剂、调理剂",
        "主要用途": "具有优良的杀菌、抗菌、防腐、抗静电、缓蚀、润湿、渗透、分散、乳化、发泡能力。耐光。耐酸。耐硬水。无积累毒性。不能与氯酚类杀菌剂共用。对杀灭硫酸盐还原菌有特效。作为杀菌剂、调理剂等，广泛应用于香波等个人护理用品领域。",
        "副反应": "具有刺激性。对皮肤、眼睛有较强的刺激性。"
    },
    {
        "英文名称": "BENZALKONIUM SACCHARINATE",
        "中文名称": "苯扎糖精铵",
        "功能": "杀菌剂、防腐剂",
        "主要用途": "固体或液体；可溶于水；稳定。具有优良的杀菌、抗菌、灭藻、防腐、抗静电、润湿、渗透、分散、乳化能力。作为杀菌剂、防腐剂等，应用于香波等个人护理用品领域。不在欧盟官方许可之内。",
        "副反应": "具有刺激性。对皮肤、眼睛有较强的刺激性。"
    },
    {
        "英文名称": "BENZYL ALCOHOL",
        "中文名称": "苯甲醇",
        "功能": "防腐剂、香料、溶剂、降粘剂",
        "主要用途": "无色至微黄色液体；具有微弱芳香气味；稳定。具有优良的抗菌、防腐、去污、增溶能力。作为防腐剂、香料、溶剂、降粘剂等，应用于个人护理用品领域。",
        "副反应": "刺激。对皮肤、眼睛有刺激性。"
    },
    {
        "英文名称": "BORIC ACID",
        "中文名称": "硼酸",
        "功能": "缓冲剂、变性剂、抗菌剂",
        "主要用途": "缓冲剂、变性剂、抗菌剂、口腔粘膜用药",
        "副反应": "在CIR(Cosmetic Ingredient Review)的报告中指出，在化妆品中浓度低于5%时属于安全添加范围，但应避免使用于婴儿或受伤肌肤上。"
    },
    {
        "英文名称": "BUTYL THIOGLYCOLATE",
        "中文名称": "巯基乙酸丁酯",
        "功能": "防腐剂、脱毛剂、染烫发剂",
        "主要用途": "液体；微溶于水；稳定。强酸、强碱下，易水解。易氧化。具有优良的抗氧化、分散能力。作为防腐剂、脱毛剂、染烫发剂等，应用于个人护理用品领域。",
        "副反应": "刺激。对皮肤、眼睛有刺激性。"
    },
    {
        "英文名称": "CALCIUM THIOGLYCOLATE",
        "中文名称": "巯基乙酸钙",
        "功能": "脱毛剂、去角质剂、还原剂",
        "主要用途": "白色至微黄色固体粉末；易溶于水；稳定；易氧化。具有优良的抗氧化、毛发脱除能力。作为脱毛剂、去角质剂、还原剂等，应用于染烫发剂、脱毛剂等个人护理用品领域。",
        "副反应": "具有刺激性。对皮肤、眼睛有刺激性。"
    },
    {
        "英文名称": "CAPRAMIDE DEA",
        "中文名称": "癸酰胺胺 DEA",
        "功能": "表面活性剂",
        "主要用途": "\r\n\r\n微黄色至棕黄色液体。可溶于水，稳定性高。对皮肤和眼睛有刺激性。对环境可能有害，可降解。有优良的去污、乳化、分散、发泡、稳泡、抗静电、增稠能力。作为调理剂、稳泡剂、抗静电剂、发泡剂、增稠剂等，应用于个人护理用品领域。",
        "副反应": "暂未见相关报道"
    },
    {
        "英文名称": "CETALKONIUM CHLORIDE",
        "中文名称": "西他氯铵",
        "功能": "消毒剂、杀菌剂",
        "主要用途": "\r\n该物质对多种口腔致病和非致病菌有抑制和杀灭作用。含漱后能减少蛀牙，减少或抑制牙菌班的形成；具有保持口腔清洁、消除口腔异味的作用。",
        "副反应": "暂未见相关报道"
    },
    {
        "英文名称": "CETEARALKONIUM BROMIDE",
        "中文名称": "鲸蜡硬脂基三甲基溴化胺",
        "功能": "调理",
        "主要用途": "一种表面活性剂。用于头发调理，可用于预防和治疗脱发症。",
        "副反应": "暂未见相关报道"
    },
    {
        "英文名称": "CETYLAMINE HYDROFLUORIDE",
        "中文名称": "鲸蜡基胺氢氟酸盐",
        "功能": "中间体",
        "主要用途": "\r\n固体。微溶于水。稳定性高。对皮肤和眼睛有刺激性。对环境可能有害，尤其是水体。可降解。作为防龋齿剂、去牙斑剂、口腔护理等，应用于个人护理用品领域。",
        "副反应": "暂未见相关报道"
    },
    {
        "英文名称": "CHLORAMINE T",
        "中文名称": "氯胺 T",
        "功能": "消毒剂",
        "主要用途": "消毒、杀菌",
        "副反应": "暂未见相关报道"
    },
    {
        "英文名称": "COCAMIDE DEA",
        "中文名称": "椰油酰胺 DEA",
        "功能": "表面活性剂",
        "主要用途": "\r\n全称椰子油二二乙醇酰胺，也叫做椰子油酸二乙醇胺。可以作为乳化剂，也是洗涤产品的原料之一。化妆品中作为表面活性剂。",
        "副反应": "暂未见相关报道"
    },
    {
        "英文名称": "COCOYL SARCOSINAMIDE DEA",
        "中文名称": "椰油酰胺基肌氨酰胺 DEA",
        "功能": "表面活性剂",
        "主要用途": "一种表面活性剂，可用作乳化，洗涤方面的原料。",
        "副反应": "暂未见相关报道"
    },
    {
        "英文名称": "4,4'-DIAMINODIPHENYLAMINE",
        "中文名称": "4,4'-二氨基二苯胺",
        "功能": "乳化剂",
        "主要用途": "一种生物化工产品",
        "副反应": "暂未见相关报道"
    },
    {
        "英文名称": "4,4'-DIAMINODIPHENYLAMINE SULFATE",
        "中文名称": "4,4'-二氨基二苯胺硫酸盐",
        "功能": "中间体",
        "主要用途": "\r\n黑色基B主要用于棉织物的染色和印花，也用于粘胶纤维的染色。与色酚AS、AS-D偶合染蓝色。偶合能力弱，偶合速度中等。也用作染料的中间体。",
        "副反应": "暂未见相关报道"
    },
    {
        "英文名称": "2,4-DIAMINOPHENOL",
        "中文名称": "2,4-二氨基苯酚",
        "功能": "乳化剂",
        "主要用途": "在化妆品中作为乳化剂使用。",
        "副反应": "暂未见相关报道"
    },
    {
        "英文名称": "2,4-DIAMINOPHENOL DIHYDROCHLORIDE",
        "中文名称": "2,4-二氨基苯酚二盐酸",
        "功能": "染色剂",
        "主要用途": "\r\n可用作摄影显影剂。在无碱有水溶液中也能显影。作高温显影液，但不能长时间保存。也用于皮毛及毛发染色，甲醛及氨的测试。在化妆品中作为染色剂使用。",
        "副反应": "暂未见相关报道"
    },
    {
        "英文名称": "2,4-DIAMINOPHENOL HCL",
        "中文名称": "2,4-二氨基苯酚 HCL",
        "功能": "表面活性剂",
        "主要用途": "\r\n可用作显像剂和皮毛染料，并用作化学试剂。在化妆品中主要作为表面活性剂使用。",
        "副反应": "暂未见相关报道"
    },
    {
        "英文名称": "DIBUTYL OXALATE",
        "中文名称": "草酸二丁酯",
        "功能": "溶剂",
        "主要用途": "\r\n无色高沸点液体。略有香味与酮、醇、油互溶。还可作有机合成反应的溶剂",
        "副反应": "暂未见相关报道"
    },
    {
        "英文名称": "DICHLOROMETHANE",
        "中文名称": "二氯甲烷",
        "功能": "发泡剂",
        "主要用途": "\r\n无色液体，在制药工业中做反应介质，用于制备氨苄青霉素、羟苄青霉素和先锋霉素等；还用作胶片生产中的溶剂、石油脱蜡溶剂、气溶胶推进剂、有机合成萃取剂、聚氨酯等泡沫塑料生产用发泡剂和金属清洗剂等。",
        "副反应": "暂未见相关报道"
    },
    {
        "英文名称": "DICHLOROPHENE",
        "中文名称": "双氯酚",
        "功能": "杀菌剂",
        "主要用途": "\r\n作杀菌灭藻剂。是法国\"G-4\"杀菌剂的主要成分。在大型化肥厂冷却水系统中使用，作用24h，杀菌率超过98%。改品在农业上、医药上、制造肥皂中可作杀菌剂使用。同时也是一种抗蠕虫药物。在化妆品中主要作为杀菌剂使用。",
        "副反应": "暂未见相关报道"
    },
    {
        "英文名称": "DIETHANOLAMINOOLEAMIDE DEA",
        "中文名称": "二羟乙氨基油酰胺 DEA",
        "功能": "发泡剂",
        "主要用途": "用于化妆品中留置型发泡化妆品组合物的发泡剂。",
        "副反应": "暂未见相关报道"
    },
    {
        "英文名称": "DIETHYL OXALATE",
        "中文名称": "草酸二乙酯",
        "功能": "中间体、增塑剂",
        "主要用途": "\r\n一种无色油状液体，有芳香气味。与乙醇、乙醚、丙酮等常见溶剂混溶，微溶于水。用作药物苯巴比妥、硫锉嘌呤、固效磺胺的中间体及增塑剂。",
        "副反应": "暂未见相关报道"
    },
    {
        "英文名称": "DIISOPROPYL OXALATE",
        "中文名称": "草酸二异丙酯",
        "功能": "表面活性剂",
        "主要用途": "在化妆品中作为表面活性剂使用。",
        "副反应": "暂未见相关报道"
    },
    {
        "英文名称": "DILITHIUM OXALATE",
        "中文名称": "草酸二锂",
        "功能": "表面活性剂",
        "主要用途": "在化妆品中作为表面活性剂使用。",
        "副反应": "暂未见相关报道"
    },
    {
        "英文名称": "DIMETHYL OXALATE",
        "中文名称": "草酸二甲酯",
        "功能": "增塑剂",
        "主要用途": "\r\n用于有机合成。用作维生素B13的中间体，也可以用作增塑剂。主要用于制药、农药、有机合成，用于纯甲醇的制备。在化妆品中主要作为增塑剂使用。",
        "副反应": "暂未见相关报道"
    },
    {
        "英文名称": "DIPOTASSIUM OXALATE",
        "中文名称": "草酸二钾",
        "功能": "增塑剂",
        "主要用途": "\r\n用于有机合成，用作维生素B13的中间体，也可用作增塑剂。化妆品中主要作为增塑剂使用。",
        "副反应": "暂未见相关报道"
    },
    {
        "英文名称": "ETHANOLAMINE",
        "中文名称": "乙醇胺",
        "功能": "\r\n表面活性剂",
        "主要用途": "抑制腐蚀等功能\r\n",
        "副反应": "暂未见相关报道"
    },
    {
        "英文名称": "ETHANOLAMINE THIOGLYCOLATE",
        "中文名称": "巯基乙酸乙醇胺盐",
        "功能": "表面活性剂",
        "主要用途": "在化妆品中作为表面活性剂使用。",
        "副反应": "暂未见相关报道"
    },
    {
        "英文名称": "ETHYL THIOGLYCOLATE",
        "中文名称": "巯基乙酸乙酯",
        "功能": "表面活性剂",
        "主要用途": "在化妆品中起乳化等作用。",
        "副反应": "暂未见相关报道"
    },
    {
        "英文名称": "ETIDRONIC ACID",
        "中文名称": "依替膦酸",
        "功能": "调节",
        "主要用途": "\r\n为骨代谢调节药。对体内磷酸钙有较强的亲和力，能抑制人体异常钙化和过量骨吸收，减轻骨痛。",
        "副反应": "暂未见相关报道"
    },
    {
        "英文名称": "FORMALDEHYDE",
        "中文名称": "甲醛",
        "功能": "\r\n防腐剂、杀菌剂",
        "主要用途": "用于化妆品防腐杀菌。",
        "副反应": "暂未见相关报道"
    },
    {
        "英文名称": "GLYCERYL THIOGLYCOLATE",
        "中文名称": "甘油巯基乙酸酯",
        "功能": "表面活性剂",
        "主要用途": "用于烫发剂的添加成分等。",
        "副反应": "暂未见相关报道"
    },
    {
        "英文名称": "HYDROGEN PEROXIDE",
        "中文名称": "过氧化氢",
        "功能": "发色",
        "主要用途": "\r\n染料染色后发色",
        "副反应": "暂未见相关报道"
    },
    {
        "英文名称": "HYDROGENATED TALLOWALKONIUM CHLORIDE",
        "中文名称": "氢化牛脂烷基二甲基苄基氯化铵",
        "功能": "表面活性剂",
        "主要用途": "用于控油护肤品，对控制皮脂在面部皮肤上分布有一定作用。",
        "副反应": "暂未见相关报道"
    },
    {
        "英文名称": "HYDROGENATED TALLOWAMIDE DEA",
        "中文名称": "氢化牛脂酰胺 DEA",
        "功能": "表面活性剂",
        "主要用途": "用途广泛的精细化工产品。",
        "副反应": "暂未见相关报道"
    },
    {
        "英文名称": "HYDROQUINONE",
        "中文名称": "氢醌",
        "功能": "染色剂",
        "主要用途": "\r\n\r\n多用于化妆品的染发剂",
        "副反应": "暂未见相关报道"
    },
    {
        "英文名称": "HYDROXYPROPYL BIS(N-HYDROXYETHYL p-PHENYLENEDIAMINE)HCL",
        "中文名称": "羟丙基双（N-羟乙基对笨二胺）HCl",
        "功能": "染色剂",
        "主要用途": "\r\n用于染发剂中的头发染色和增亮等功能。",
        "副反应": "暂未见相关报道"
    },
    {
        "英文名称": "ISOOCTYL THIOGLYCOLATE",
        "中文名称": "巯基乙酸异辛酯",
        "功能": "\r\n稳定剂、增塑剂",
        "主要用途": "用于化妆品的稳定剂和增塑剂。",
        "副反应": "暂未见相关报道"
    },
    {
        "英文名称": "ISOPROPANOLAMINE",
        "中文名称": "异丙醇胺",
        "功能": "乳化剂",
        "主要用途": "\r\n是有机合成中间体，用于化妆品乳化剂的使用。",
        "副反应": "暂未见相关报道"
    }
]